lib_shopify_graphql/__init__.py
lib_shopify_graphql/__init__conf__.py
lib_shopify_graphql/__main__.py
lib_shopify_graphql/_compat.py
lib_shopify_graphql/composition.py
lib_shopify_graphql/config.py
lib_shopify_graphql/config_deploy.py
lib_shopify_graphql/config_show.py
lib_shopify_graphql/defaultconfig.toml
lib_shopify_graphql/enums.py
lib_shopify_graphql/exceptions.py
lib_shopify_graphql/logging_setup.py
lib_shopify_graphql/py.typed
lib_shopify_graphql/adapters/__init__.py
lib_shopify_graphql/adapters/cache_json.py
lib_shopify_graphql/adapters/cache_mysql.py
lib_shopify_graphql/adapters/constants.py
lib_shopify_graphql/adapters/location_resolver.py
lib_shopify_graphql/adapters/mutations.py
lib_shopify_graphql/adapters/parsers.py
lib_shopify_graphql/adapters/queries.py
lib_shopify_graphql/adapters/shopify_sdk.py
lib_shopify_graphql/adapters/sku_resolver.py
lib_shopify_graphql/adapters/token_cache.py
lib_shopify_graphql/application/__init__.py
lib_shopify_graphql/application/ports.py
lib_shopify_graphql/cli/__init__.py
lib_shopify_graphql/cli/_cache.py
lib_shopify_graphql/cli/_common.py
lib_shopify_graphql/cli/_config.py
lib_shopify_graphql/cli/_health.py
lib_shopify_graphql/cli/_images.py
lib_shopify_graphql/cli/_products.py
lib_shopify_graphql/cli/_test_limits.py
lib_shopify_graphql/defaultconfig.d/10-logging.toml
lib_shopify_graphql/defaultconfig.d/20-shopify.toml
lib_shopify_graphql/defaultconfig.d/30-mysql.toml
lib_shopify_graphql/defaultconfig.d/40-token-cache.toml
lib_shopify_graphql/defaultconfig.d/50-sku-cache.toml
lib_shopify_graphql/defaultconfig.d/60-graphql.toml
lib_shopify_graphql/domain/__init__.py
lib_shopify_graphql/models/__init__.py
lib_shopify_graphql/models/_entities.py
lib_shopify_graphql/models/_enums.py
lib_shopify_graphql/models/_images.py
lib_shopify_graphql/models/_internal.py
lib_shopify_graphql/models/_mutations.py
lib_shopify_graphql/models/_operations.py
lib_shopify_graphql/shopify_client/__init__.py
lib_shopify_graphql-2.0.1.dist-info/METADATA
lib_shopify_graphql-2.0.1.dist-info/WHEEL
lib_shopify_graphql-2.0.1.dist-info/entry_points.txt
lib_shopify_graphql-2.0.1.dist-info/licenses/LICENSE
lib_shopify_graphql-2.0.1.dist-info/RECORD
